{
  "callLogs": [
    {
      "id": "0e2e",
      "number": "6505551212",
      "timeStamp": "2025-07-11T01:01:13.974Z",
      "state": "INCOMING_CALL"
    },
    {
      "id": "ece1",
      "number": "6505551212",
      "timeStamp": "2025-07-11T01:01:14.024Z",
      "state": "INCOMING_CALL"
    },
    {
      "id": "a844",
      "number": "6505551212",
      "timeStamp": "2025-07-11T01:01:13.550Z",
      "state": "INCOMING_CALL"
    },
    {
      "id": "f1c7",
      "number": "6505551212",
      "timeStamp": "2025-07-11T01:01:14.077Z",
      "state": "INCOMING_CALL"
    },
    {
      "id": "62bf",
      "number": "6505551212",
      "timeStamp": "2025-07-11T05:39:29.246Z",
      "state": "INCOMING_CALL"
    },
    {
      "id": "d4e6",
      "number": "6505551212",
      "timeStamp": "11/07/2025, 11:13:17",
      "state": "INCOMING_CALL"
    },
    {
      "id": "b1f9",
      "number": "6505551212",
      "timeStamp": "11/07/2025, 12:25:16",
      "state": "INCOMING_CALL"
    },
    {
      "id": "5a0b",
      "number": "6505551212",
      "timeStamp": "11/07/2025, 12:25:41",
      "state": "INCOMING_CALL"
    },
    {
      "id": "5966",
      "number": "6505551212",
      "timeStamp": "11/07/2025, 13:07:03",
      "state": "INCOMING_CALL"
    },
    {
      "id": "9c3c",
      "number": "6505551212",
      "timeStamp": "11/07/2025, 13:07:02",
      "state": "INCOMING_CALL"
    },
    {
      "id": "8c98",
      "number": "6505551212",
      "timeStamp": "11/07/2025, 13:40:25",
      "state": "INCOMING_CALL"
    },
    {
      "id": "6828",
      "number": "6505551212",
      "timeStamp": "11/07/2025, 13:40:41",
      "state": "INCOMING_CALL"
    },
    {
      "id": "2686",
      "number": "6505551212",
      "timeStamp": "11/07/2025, 13:42:00",
      "state": "INCOMING_CALL"
    },
    {
      "id": "e516",
      "number": "6505551212",
      "timeStamp": "11/07/2025, 13:42:00",
      "state": "INCOMING_CALL"
    }
  ]
}